pixela2img/__init__.py
pixela2img/__main__.py
pixela2img-2018.1.dist-info/LICENSE
pixela2img-2018.1.dist-info/METADATA
pixela2img-2018.1.dist-info/WHEEL
pixela2img-2018.1.dist-info/top_level.txt
pixela2img-2018.1.dist-info/RECORD
