Metadata-Version: 2.1
Name: pixela2img
Version: 2018.1
Summary: Create image files or objects from pixela svg graphs.
Home-page: https://github.com/ryosms/pixela2img
Author: ryosms
Author-email: UNKNOWN
License: MIT
Platform: UNKNOWN
Requires-Dist: pillow
Requires-Dist: defusedxml
Requires-Dist: requests
